[
    {
        "entrance": {
            "entranceId": ""
        },
        "eventActionType": {
            "eventActionTypeId": 9
        },
        "controller": {
            "controllerSerialNo": "100000005a46e105"
        },
        "eventTime": "07-18-2022 14:50:11"
    }
]: 1
        },
        "controller": {
            "controllerSerialNo": "100000005a46e105"
        },
        "eventTime": "07-18-2022 10:47:00"
    }
] }
]      "controllerSerialNo": null
        },
        "eventTime": "07-08-2022 11:40:56"
    },
    {
        "entrance": {
            "entranceId": 1
        },
        "eventActionType": {
            "eventActionTypeId": 9
        },
        "controller": {
            "controllerSerialNo": null
        },
        "eventTime": "07-08-2022 11:42:17"
    },
    {
        "entrance": {
            "entranceId": 1
        },
        "eventActionType": {
            "eventActionTypeId": 9
        },
        "controller": {
            "controllerSerialNo": null
        },
        "eventTime": "07-08-2022 11:45:44"
    },
    {
        "entrance": {
            "entranceId": 1
        },
        "eventActionType": {
            "eventActionTypeId": 9
        },
        "controller": {
            "controllerSerialNo": null
        },
        "eventTime": "07-08-2022 11:48:44"
    },
    {
        "entrance": {
            "entranceId": 1
        },
        "eventActionType": {
            "eventActionTypeId": 9
        },
        "controller": {
            "controllerSerialNo": null
        },
        "eventTime": "07-08-2022 11:52:44"
    }
]